odoo/addons/test_auditlog/README.rst
odoo/addons/test_auditlog/__init__.py
odoo/addons/test_auditlog/__manifest__.py
odoo/addons/test_auditlog/i18n/it.po
odoo/addons/test_auditlog/i18n/test_auditlog.pot
odoo/addons/test_auditlog/readme/CONTRIBUTORS.md
odoo/addons/test_auditlog/readme/DESCRIPTION.md
odoo/addons/test_auditlog/static/description/icon.png
odoo/addons/test_auditlog/static/description/index.html
odoo/addons/test_auditlog/tests/__init__.py
odoo/addons/test_auditlog/tests/test_account_bank_statement_line.py
odoo/addons/test_auditlog/tests/test_account_move_reverse.py
odoo/addons/test_auditlog/tests/test_product_tax_multicompany.py
odoo_addon_test_auditlog-19.0.1.0.0.3.dist-info/METADATA
odoo_addon_test_auditlog-19.0.1.0.0.3.dist-info/WHEEL
odoo_addon_test_auditlog-19.0.1.0.0.3.dist-info/top_level.txt
odoo_addon_test_auditlog-19.0.1.0.0.3.dist-info/RECORD
