Metadata-Version: 2.1
Name: odoo-addon-test_auditlog
Version: 19.0.1.0.0.3
Requires-Dist: odoo-addon-auditlog==19.0.*
Requires-Dist: odoo==19.0.*
Summary: Additional unit tests for Audit Log based on accounting models
Home-page: https://github.com/OCA/server-tools
License: AGPL-3
Author: Odoo Community Association (OCA)
Author-email: support@odoo-community.org
Classifier: Programming Language :: Python
Classifier: Framework :: Odoo
Classifier: Framework :: Odoo :: 19.0
Classifier: License :: OSI Approved :: GNU Affero General Public License v3
